zinny_webui/__init__.py
zinny_webui/cli.py
zinny_webui/config.py
zinny_webui/routes/__init__.py
zinny_webui/routes/errors.py
zinny_webui/static/favicon.ico
zinny_webui/static/css/bootstrap-grid.css
zinny_webui/static/css/bootstrap-grid.css.map
zinny_webui/static/css/bootstrap-grid.min.css
zinny_webui/static/css/bootstrap-grid.min.css.map
zinny_webui/static/css/bootstrap-grid.rtl.css
zinny_webui/static/css/bootstrap-grid.rtl.css.map
zinny_webui/static/css/bootstrap-grid.rtl.min.css
zinny_webui/static/css/bootstrap-grid.rtl.min.css.map
zinny_webui/static/css/bootstrap-icons.css
zinny_webui/static/css/bootstrap-icons.min.css
zinny_webui/static/css/bootstrap-reboot.css
zinny_webui/static/css/bootstrap-reboot.css.map
zinny_webui/static/css/bootstrap-reboot.min.css
zinny_webui/static/css/bootstrap-reboot.min.css.map
zinny_webui/static/css/bootstrap-reboot.rtl.css
zinny_webui/static/css/bootstrap-reboot.rtl.css.map
zinny_webui/static/css/bootstrap-reboot.rtl.min.css
zinny_webui/static/css/bootstrap-reboot.rtl.min.css.map
zinny_webui/static/css/bootstrap-utilities.css
zinny_webui/static/css/bootstrap-utilities.css.map
zinny_webui/static/css/bootstrap-utilities.min.css
zinny_webui/static/css/bootstrap-utilities.min.css.map
zinny_webui/static/css/bootstrap-utilities.rtl.css
zinny_webui/static/css/bootstrap-utilities.rtl.css.map
zinny_webui/static/css/bootstrap-utilities.rtl.min.css
zinny_webui/static/css/bootstrap-utilities.rtl.min.css.map
zinny_webui/static/css/bootstrap.css
zinny_webui/static/css/bootstrap.css.map
zinny_webui/static/css/bootstrap.min.css
zinny_webui/static/css/bootstrap.min.css.map
zinny_webui/static/css/bootstrap.rtl.css
zinny_webui/static/css/bootstrap.rtl.css.map
zinny_webui/static/css/bootstrap.rtl.min.css
zinny_webui/static/css/bootstrap.rtl.min.css.map
zinny_webui/static/css/styles.css
zinny_webui/static/css/fonts/bootstrap-icons.woff
zinny_webui/static/css/fonts/bootstrap-icons.woff2
zinny_webui/static/img/zinny-logo.png
zinny_webui-0.1.26.dist-info/LICENSE
zinny_webui-0.1.26.dist-info/METADATA
zinny_webui-0.1.26.dist-info/WHEEL
zinny_webui-0.1.26.dist-info/entry_points.txt
zinny_webui-0.1.26.dist-info/top_level.txt
zinny_webui-0.1.26.dist-info/RECORD
