Metadata-Version: 2.1
Name: zinny-webui
Version: 0.1.26
Summary: A Web UI for rating Motion Picture titles. Uses Zinny API
Author: Ryan Laney
License: BSD 3-Clause License
Project-URL: Homepage, https://github.com/RyLaney/zinny-webui
Project-URL: Issues, https://github.com/RyLaney/zinny-webui/issues
Keywords: zinny,surveys,movie,rating
Classifier: Programming Language :: Python :: 3
Classifier: License :: OSI Approved :: BSD License
Classifier: Operating System :: OS Independent
Requires-Python: >=3.8
License-File: LICENSE
Provides-Extra: dev
Requires-Dist: pytest; extra == "dev"
Requires-Dist: black; extra == "dev"
